{
  "network": "fantom",
  "symmioAddress": "0x155713e2F8E7bCeBB8aB107fa7377e9ca37A6F03",
  "symmioStartBlock": "68411968",
  "symmioVersion": "0.8.2",
  "multiAccounts": [
    {
      "symmioMultiAccountAddress": "0x0937bC09b8D073E4F1abE85470969475f714Ca6c",
      "symmioMultiAccountStartBlock": "57794244",
      "symmioMultiAccountName": "MultiAccount1"
    }
  ],
  "analyticsDeployUrl": "symmiograph/symmioanalytics_ftm_8",
  "mainDeployUrl": "symmiograph/symmiomain_ftm_8",
  "partiesDeployUrl": "symmiograph/symmioparties_ftm_8"
}
